firstPackageProject/__init__.py
firstPackageProject/fib.py
firstPackageProject/lib.py
astDrawer-0.0.3.dist-info/METADATA
astDrawer-0.0.3.dist-info/WHEEL
astDrawer-0.0.3.dist-info/top_level.txt
astDrawer-0.0.3.dist-info/RECORD
